efficient_first_stage_retrieval/__init__.py
efficient_first_stage_retrieval/_nbdev.py
efficient_first_stage_retrieval/core.py
efficient_first_stage_retrieval-0.0.36.dist-info/LICENSE
efficient_first_stage_retrieval-0.0.36.dist-info/METADATA
efficient_first_stage_retrieval-0.0.36.dist-info/WHEEL
efficient_first_stage_retrieval-0.0.36.dist-info/entry_points.txt
efficient_first_stage_retrieval-0.0.36.dist-info/top_level.txt
efficient_first_stage_retrieval-0.0.36.dist-info/RECORD
